era_5g_client/__init__.py
era_5g_client/client.py
era_5g_client/client_base.py
era_5g_client/dataclasses.py
era_5g_client/exceptions.py
era_5g_client/middleware_resource_checker.py
era_5g_client/py.typed
era_5g_client-1.1.0.dist-info/METADATA
era_5g_client-1.1.0.dist-info/WHEEL
era_5g_client-1.1.0.dist-info/namespace_packages.txt
era_5g_client-1.1.0.dist-info/top_level.txt
era_5g_client-1.1.0.dist-info/RECORD
